auditflow/__init__.py
auditflow/core.py
auditflow-1.0.0.dist-info/licenses/LICENSE
auditflow-1.0.0.dist-info/METADATA
auditflow-1.0.0.dist-info/WHEEL
auditflow-1.0.0.dist-info/top_level.txt
auditflow-1.0.0.dist-info/RECORD
